Workbook

Sheet 控え
B2: 請求書（控え） | AB2: 46198
B5: ご住所 | X5: 三和商事株式会社 豊岡サービスステーション
B7: お名前 | S7: 様 | X7: 〒668-0052 豊岡市九日市下町131
X8: TEL 0796-23-2030
B9: TEL | X9: 担当
B11: 車名 | G11: 車種 | R11: 初年度登録 | X11: 登録番号
B12: 三菱 | G12: ミニキャブバン | R12: 平成30年6月 | X12: 姫路 | AB12: 480 | AE12: ち | AG12: 9525
B14: 型式 | G14: 車体番号 | R14: 次回車検日 | X14: 走行距離
B15: HBD-DS17V | G15: DS17V-256638 | R15: 令和10年6月27日 | X15: 94790 | AD15: ｋｍ
B18: ご請求金額 | G18: =AH22 | O18: 円 | R18: 備考 | S18: 代行料は税込表示／REX納品書 伝票No.00016126より転記
B21: 整備合計 | F21: 消費税（10％） | J21: 自賠責 | M21: 重量税 | P21: 印紙税等 | S21: その他 | V21: 諸費用計 | Z21: 合計金額 | AD21: 調整額 | AH21: 請求金額
B22: =SUM(X46:AF46) | F22: =ROUND(B22*0.1,0) | M22: 6600 | P22: 2100 | S22: 7700 | V22: =SUM(J22:U23) | Z22: =V22+F22+B22 | AD22: -1 | AH22: =Z22+AD22
B25: № | C25: 作業内容・部品名等 | R25: 数量 | U25: 単価 | X25: 部品金額 | AB25: 技術料・他 | AG25: 摘要
B26: 1 | C26: 車検基本料金 | AB26: 11500
B27: 2 | C27: フロント・ディスク・ロータ（1台）取替 | AB27: 9000
B28: 3 | C28: ディスク, フロント ブレーキ | R28: 2 | AG28: 持込
B29: 4 | C29: パッド, セット, フロント ブレーキ | R29: 1 | AG29: 持込
B30: 5 | C30: リヤブレーキ（1台）清掃 | AB30: 2700
B31: 6 | C31: ブレーキ・フルード 取替 | R31: 1 | U31: 1000 | X31: 1000 | AB31: 2700
B32: 7 | C32: V-ベルト全数 取替 | AB32: 8100
B33: 8 | C33: ベルト, エアコン | R33: 1 | AG33: 持込
B34: 9 | C34: ベルト, オルタネータ＆アイドラ | R34: 1 | AG34: 持込
B35: 10 | C35: エア・クリーナー・エレメント 取替 | AB35: 2700
B36: 11 | C36: エレメント, エア クリーナ | R36: 1 | AG36: 持込
B37: 12 | C37: 発炎筒 取付 | R37: 1 | AG37: 持込
B38: 13 | C38: フロントバンパークリップ 取付 | R38: 1 | AG38: 持込
B39: 14 | C39: アンダーカバークリップ 取付 | R39: 2 | AG39: 持込
B40: 15 | C40: スペアタイヤ・エアバルブ 取替 | R40: 1 | U40: 1000 | X40: 1000 | AB40: 1000
B41: 16 | C41: 燃ポンプデリ・エアコンフィルター（スタンドにて） | AB41: -5245 | AG41: 値引
B42: 17
B43: 18
B44: 19
B45: 20
B46: ※ | R46: 小計金額 | X46: =SUM(X26:AA45) | AB46: =SUM(AB26:AF45)

Sheet 請求書
B2: 請求書 | AB2: =TODAY()
B5: ご住所 | F5: =控え!F5 | X5: 三和商事株式会社 豊岡サービスステーション
F6: =控え!F6
B7: お名前 | F7: =控え!F7 | S7: 様 | X7: 〒668-0052 豊岡市九日市下町131
X8: TEL 0796-23-2030
B9: TEL | F9: =控え!F9 | X9: 担当 | AB9: =控え!AB9
B11: 車名 | G11: 車種 | R11: 初年度登録 | X11: 登録番号
B12: =控え!B12 | G12: =控え!G12 | R12: =控え!R12 | X12: =控え!X12 | AB12: =控え!AB12 | AE12: =控え!AE12 | AG12: =控え!AG12
B14: 型式 | G14: 車体番号 | R14: 次回車検日 | X14: 走行距離
B15: =控え!B15 | G15: =控え!G15 | R15: =控え!R15 | X15: =控え!X15 | AD15: ｋｍ
B18: ご請求金額 | G18: =控え!G18 | O18: 円
B21: 整備合計 | F21: 消費税（10％） | J21: 自賠責 | M21: 重量税 | P21: 印紙税等 | S21: その他 | V21: 諸費用計 | Z21: 合計金額 | AD21: 調整額 | AH21: 請求金額
B22: =控え!B22 | F22: =控え!F22 | J22: =控え!J22 | M22: =控え!M22 | P22: =控え!P22 | S22: =控え!S22 | V22: =控え!V22 | Z22: =控え!Z22 | AD22: =控え!AD22 | AH22: =控え!AH22
B25: № | C25: 作業内容・部品名等 | R25: 数量 | U25: 単価 | X25: 部品金額 | AB25: 技術料・他 | AG25: 摘要
B26: 1 | C26: =控え!C26 | R26: =控え!R26 | U26: =控え!U26 | X26: =控え!X26 | AB26: =控え!AB26 | AG26: =控え!AG26
B27: 2 | C27: =控え!C27 | R27: =控え!R27 | U27: =控え!U27 | X27: =控え!X27 | AB27: =控え!AB27 | AG27: =控え!AG27
B28: 3 | C28: =控え!C28 | R28: =控え!R28 | U28: =控え!U28 | X28: =控え!X28 | AB28: =控え!AB28 | AG28: =控え!AG28
B29: 4 | C29: =控え!C29 | R29: =控え!R29 | U29: =控え!U29 | X29: =控え!X29 | AB29: =控え!AB29 | AG29: =控え!AG29
B30: 5 | C30: =控え!C30 | R30: =控え!R30 | U30: =控え!U30 | X30: =控え!X30 | AB30: =控え!AB30 | AG30: =控え!AG30
B31: 6 | C31: =控え!C31 | R31: =控え!R31 | U31: =控え!U31 | X31: =控え!X31 | AB31: =控え!AB31 | AG31: =控え!AG31
B32: 7 | C32: =控え!C32 | R32: =控え!R32 | U32: =控え!U32 | X32: =控え!X32 | AB32: =控え!AB32 | AG32: =控え!AG32
B33: 8 | C33: =控え!C33 | R33: =控え!R33 | U33: =控え!U33 | X33: =控え!X33 | AB33: =控え!AB33 | AG33: =控え!AG33
B34: 9 | C34: =控え!C34 | R34: =控え!R34 | U34: =控え!U34 | X34: =控え!X34 | AB34: =控え!AB34 | AG34: =控え!AG34
B35: 10 | C35: =控え!C35 | R35: =控え!R35 | U35: =控え!U35 | X35: =控え!X35 | AB35: =控え!AB35 | AG35: =控え!AG35
B36: 11 | C36: =控え!C36 | R36: =控え!R36 | U36: =控え!U36 | X36: =控え!X36 | AB36: =控え!AB36 | AG36: =控え!AG36
B37: 12 | C37: =控え!C37 | R37: =控え!R37 | U37: =控え!U37 | X37: =控え!X37 | AB37: =控え!AB37 | AG37: =控え!AG37
... B45: 20 | C45: =控え!C45 | R45: =控え!R45 | U45: =控え!U45 | X45: =控え!X45 | AB45: =控え!AB45 | AG45: =控え!AG45
B46: ※ | C46: =控え!C46 | R46: 小計金額 | X46: =控え!X46 | AB46: =控え!AB46 | AG46: =控え!AG46
B48: =控え!B48
B49: =控え!B49
B50: =控え!B50

Sheet 社内集計
D3: 車検基本料金 | K3: 代行料 | R3: ショートパーツ
B4: 税別
Q6: 三和部品
L7: 税別
G10: 売上 | L10: 仕入
G11: 税込 | L11: ｒｅｘ税込 | Q11: 三和部品 | V11: 粗利
C12: 法定費用 | G12: =控え!V22 | V12: =G12-L12-Q12
C13: 車検基本料金 | G13: =ROUND(控え!AB26*1.1,0) | L13: =(D4+K4+R4)*1.1 | V13: =G13-L13-Q13
C14: 部品代 | G14: =ROUND(控え!X46*1.1,0) | Q14: =ROUND(Q7*1.1,0) | V14: =G14-L14-Q14
C15: 技術料 | G15: =ROUND((控え!AB46-控え!AB26)*1.1,0) | V15: =G15-L15-Q15
V16: =G16-L16-Q16
V17: =G17-L17-Q17
C18: 合計 | G18: =SUM(G12:K17) | L18: =SUM(L12:P17) | Q18: =SUM(Q12:U17) | V18: =G18-L18-Q18
C19: 請求金額 | G19: =控え!G18 | Q19: =ROUND(Q7*1.1,0) | V19: =G19-L19-Q19
C20: 調整 | G20: =G18-G19 | L20: =L18-L19 | Q20: =Q18-Q19 | V20: =G20-控え!Y34-Q20
C22: 部品代 | I22: 売上 | M22: =G14 | Q22: 仕入 | U22: =(L14+Q14)/1.1
C23: 技術料 | I23: 売上 | M23: =G15 | Q23: 仕入 | U23: =L15/1.1
I24: 【税込） | Q24: 【税別）
C26: 法定費用 | I26: =G12 | N26: まとめて入力
C28: 車検基本料金 | J28: 売上 | N28: =G13 | R28: 仕入れ | V28: =L13/1.1
J29: 【税込） | R29: 【税別）
